precursorupdater/__init__.py
precursorupdater/__main__.py
precursorupdater/precursorupdater.py
precursorupdater/precursorusb/__init__.py
precursorupdater/precursorusb/precursorusb.py
precursorupdater-0.0.6.dist-info/LICENSE
precursorupdater-0.0.6.dist-info/METADATA
precursorupdater-0.0.6.dist-info/WHEEL
precursorupdater-0.0.6.dist-info/entry_points.txt
precursorupdater-0.0.6.dist-info/top_level.txt
precursorupdater-0.0.6.dist-info/RECORD
