Metadata-Version: 2.1
Name: precursorupdater
Version: 0.0.6
Summary: Precursor USB Updater
Home-page: https://github.com/betrusted-io/betrusted-wiki/wiki/Updating-Your-Device
Author: bunnie
License: Apache2.0
Project-URL: Bug Tracker, https://github.com/betrusted-io/xous-core/issues
Project-URL: Documentation, https://github.com/betrusted-io/betrusted-wiki/wiki/Updating-Your-Device
Project-URL: Source Code, https://github.com/betrusted-io/xous-core/tree/main/tools/updater
Classifier: Programming Language :: Python :: 3
Classifier: License :: OSI Approved :: Apache Software License
Classifier: Operating System :: OS Independent
Classifier: Development Status :: 3 - Alpha
Classifier: Environment :: Console
Classifier: Topic :: System :: Hardware
Classifier: Topic :: System :: Hardware :: Universal Serial Bus (USB)
License-File: LICENSE
Requires-Dist: requests (>=2)
Requires-Dist: pyusb (>=1)
Requires-Dist: progressbar2 (>=3)
